airflow_provider_db2/__init__.py
airflow_provider_db2/hooks/db2_hook.py
airflow_provider_db2-0.0.4.dist-info/LICENSE
airflow_provider_db2-0.0.4.dist-info/METADATA
airflow_provider_db2-0.0.4.dist-info/WHEEL
airflow_provider_db2-0.0.4.dist-info/entry_points.txt
airflow_provider_db2-0.0.4.dist-info/top_level.txt
airflow_provider_db2-0.0.4.dist-info/RECORD
