Metadata-Version: 2.1
Name: airflow-provider-db2
Version: 0.0.4
Summary: A provider package built by AIOPS IBM team
Home-page: UNKNOWN
Author: Fernanda Milagres
Author-email: fernandamilagres@gmail.com
License: Apache License 2.0
Platform: UNKNOWN
Requires-Python: >=3
License-File: LICENSE
Requires-Dist: apache-airflow (>=2.0)
